{
  "main": {
    "id": "248aa672f84b4072",
    "type": "split",
    "children": [
      {
        "id": "f16c6985c7ebfb0a",
        "type": "tabs",
        "children": [
          {
            "id": "c2b40c9adacedbf9",
            "type": "leaf",
            "pinned": true,
            "state": {
              "type": "markdown",
              "state": {
                "file": "Home.md",
                "mode": "source",
                "source": false
              },
              "pinned": true
            }
          },
          {
            "id": "247a97a88d8eabb4",
            "type": "leaf",
            "state": {
              "type": "markdown",
              "state": {
                "file": "Django Info/Django - Información de Configuración.md",
                "mode": "source",
                "source": false
              }
            }
          },
          {
            "id": "e3d6530d80e6ab00",
            "type": "leaf",
            "state": {
              "type": "markdown",
              "state": {
                "file": "GRC - Governability Risk Compliance/How to Make Sense of Cybersecurity Frameworks - video.md",
                "mode": "source",
                "source": false
              }
            }
          },
          {
            "id": "dabc2df646a0930e",
            "type": "leaf",
            "state": {
              "type": "markdown",
              "state": {
                "file": "Comandos bash/Comando du.md",
                "mode": "source",
                "source": false
              }
            }
          },
          {
            "id": "afd30415ba3bce97",
            "type": "leaf",
            "state": {
              "type": "markdown",
              "state": {
                "file": "Comandos bash/Comando df.md",
                "mode": "source",
                "source": false
              }
            }
          },
          {
            "id": "4fa3c8caa5d788dd",
            "type": "leaf",
            "state": {
              "type": "markdown",
              "state": {
                "file": "Linux Hacking/Kali Linux post-instalacion.md",
                "mode": "source",
                "source": false
              }
            }
          },
          {
            "id": "37ce8254497f604a",
            "type": "leaf",
            "state": {
              "type": "markdown",
              "state": {
                "file": "Django Info/Deploy Django/deploy_pythonanywhere_django3.2.md",
                "mode": "source",
                "source": false
              }
            }
          },
          {
            "id": "8eaf219f187b9497",
            "type": "leaf",
            "pinned": true,
            "state": {
              "type": "markdown",
              "state": {
                "file": "GRC - Governability Risk Compliance/Gestión del cambio en las organizaciones.md",
                "mode": "source",
                "source": false
              },
              "pinned": true
            }
          }
        ],
        "currentTab": 5
      }
    ],
    "direction": "vertical"
  },
  "left": {
    "id": "1b43f4b53f321daa",
    "type": "split",
    "children": [
      {
        "id": "57243f419742c698",
        "type": "tabs",
        "children": [
          {
            "id": "f84e3464eceb0694",
            "type": "leaf",
            "state": {
              "type": "file-explorer",
              "state": {
                "sortOrder": "alphabetical"
              }
            }
          },
          {
            "id": "8be9135be055b7ce",
            "type": "leaf",
            "state": {
              "type": "search",
              "state": {
                "query": "comando dig",
                "matchingCase": false,
                "explainSearch": false,
                "collapseAll": false,
                "extraContext": false,
                "sortOrder": "alphabetical"
              }
            }
          },
          {
            "id": "e6b208b8891bc83e",
            "type": "leaf",
            "state": {
              "type": "bookmarks",
              "state": {}
            }
          }
        ]
      }
    ],
    "direction": "horizontal",
    "width": 257.5
  },
  "right": {
    "id": "aeb1996e648a0195",
    "type": "split",
    "children": [
      {
        "id": "ea6bff1ec15a759d",
        "type": "tabs",
        "children": [
          {
            "id": "f3ce04e868dd7671",
            "type": "leaf",
            "state": {
              "type": "backlink",
              "state": {
                "file": "Linux Hacking/Kali Linux post-instalacion.md",
                "collapseAll": false,
                "extraContext": false,
                "sortOrder": "alphabetical",
                "showSearch": false,
                "searchQuery": "",
                "backlinkCollapsed": false,
                "unlinkedCollapsed": true
              }
            }
          },
          {
            "id": "5bc3a37cd197dcf9",
            "type": "leaf",
            "state": {
              "type": "outgoing-link",
              "state": {
                "file": "Linux Hacking/Kali Linux post-instalacion.md",
                "linksCollapsed": false,
                "unlinkedCollapsed": true
              }
            }
          },
          {
            "id": "479779db9e285e8e",
            "type": "leaf",
            "state": {
              "type": "tag",
              "state": {
                "sortOrder": "frequency",
                "useHierarchy": false
              }
            }
          },
          {
            "id": "61da7e846f8756ff",
            "type": "leaf",
            "state": {
              "type": "outline",
              "state": {
                "file": "Linux Hacking/Kali Linux post-instalacion.md"
              }
            }
          },
          {
            "id": "1c6dee1f233e014f",
            "type": "leaf",
            "state": {
              "type": "all-properties",
              "state": {
                "sortOrder": "frequency",
                "showSearch": false,
                "searchQuery": ""
              }
            }
          }
        ],
        "currentTab": 3
      }
    ],
    "direction": "horizontal",
    "width": 308.5
  },
  "left-ribbon": {
    "hiddenItems": {
      "switcher:Open quick switcher": false,
      "graph:Open graph view": false,
      "canvas:Create new canvas": false,
      "daily-notes:Open today's daily note": false,
      "templates:Insert template": false,
      "command-palette:Open command palette": false,
      "webpage-html-export:Export Vault to HTML": false
    }
  },
  "active": "4fa3c8caa5d788dd",
  "lastOpenFiles": [
    "Comandos bash/Comando df.md",
    "Comandos bash/Comando du.md",
    "Linux Hacking/Conocer el espacio disponible en disco.md",
    "Comandos bash/Comando dig.md",
    "Comandos bash/Comando dirb.md",
    "Comandos bash/Comando nmap.md",
    "Linux Hacking/Atacar Metasploitable 2.md",
    "GRC - Governability Risk Compliance/How to Make Sense of Cybersecurity Frameworks - article.md",
    "GRC - Governability Risk Compliance/NIST CSF/NIST.CSWP.29.pdf",
    "GRC - Governability Risk Compliance/How to Make Sense of Cybersecurity Frameworks - video.md",
    "Linux Hacking/Herramienta Tenable Nessus.md",
    "Linux Hacking/archivos/Selección_1375.png",
    "Linux Hacking/archivos/Selección_1377.png",
    "Linux Hacking/archivos/Selección_1374.png",
    "Linux Hacking/archivos/Selección_1372b.png",
    "Linux Hacking/archivos/Selección_1372.png",
    "Linux Hacking/archivos/Selección_1371.png",
    "Linux Hacking/archivos/Selección_1370.png",
    "Linux Hacking/archivos/Selección_1379.png",
    "Linux Hacking/archivos/Selección_1369.png",
    "Linux Hacking/archivos/Selección_1364.png",
    "Django Info/Deploy Django/deploy_pythonanywhere_django3.2.md",
    "Linux Hacking/archivos",
    "Linux Hacking/Herramienta BurpSuite.md",
    "Linux Hacking/Conectarse con ssh.md",
    "Linux Hacking/Atacar DVWA.md",
    "Linux Hacking/Kali Linux post-instalacion.md",
    "Ciberseguridad.md",
    "Linux Hacking/Ubuntu Touch - Google Pixel 3a.md",
    "Normativa/Leyes Ciberseguridad Chile.md",
    "Normativa/Ley 21.459.md",
    "Normativa/Ley-21459_20-JUN-2022_firmado.pdf",
    "Normativa/Ley-21459_20-JUN-2022.pdf",
    "Conceptos/Recopilacion de informacion.md",
    "Conceptos/Resolución de problemas.md",
    "Django Info/Deploy Django/deploy_cpanel_django3.2.md",
    "Django Info/Deploy Django/migrar_bd_sqlite_mysql.md",
    "Django Info/Advanced Django Cheat Sheet.md",
    "Django Info/Datos iniciales GitHub.md",
    "Django Info/Django - Información de Configuración.md",
    "GRC - Governability Risk Compliance/ISO 270XX/curso uchile/PPT_Norma27001.pdf",
    "GRC - Governability Risk Compliance/ISO 270XX/curso uchile/PPT_Controles_del_Anexo_A_de_27001_2022.pdf",
    "GRC - Governability Risk Compliance/ISO 270XX/curso uchile/Interacciones_de_un_SGS_en_ISO_27001_2022.pdf",
    "GRC - Governability Risk Compliance/ISO 31000/ISO 31000 2018 ES.pdf",
    "GRC - Governability Risk Compliance/ISO 270XX/ISO 27004-2010.pdf",
    "CURSOS/Uchile"
  ]
}